netchecker/__init__.py
netchecker/utils.py
netchecker-1.0.2.dist-info/METADATA
netchecker-1.0.2.dist-info/WHEEL
netchecker-1.0.2.dist-info/licenses/LICENSE
netchecker-1.0.2.dist-info/RECORD
