Metadata-Version: 2.4
Name: netchecker
Version: 1.0.2
Summary: A simple yet powerful Python module to check internet and DNS capabilities of a system.
Project-URL: Homepage, https://github.com/PowerPCFan/netchecker
Project-URL: Issues, https://github.com/PowerPCFan/netchecker/issues
Author-email: PowerPCFan <charlie@powerpcfan.xyz>
Maintainer-email: PowerPCFan <charlie@powerpcfan.xyz>
License-Expression: AGPL-3.0-only
License-File: LICENSE
Classifier: Operating System :: OS Independent
Classifier: Programming Language :: Python
Classifier: Programming Language :: Python :: 3
Classifier: Programming Language :: Python :: 3.10
Classifier: Programming Language :: Python :: 3.11
Classifier: Programming Language :: Python :: 3.12
Classifier: Programming Language :: Python :: 3.13
Requires-Python: >=3.10
Requires-Dist: icmplib>=3.0.4
